awss/__init__.py
awss/__main__.py
awss/acm.py
awss/ec2.py
awss/lib.py
awss/rds.py
awss/sts.py
aws_multi_region_search-0.1.0.dist-info/LICENSE
aws_multi_region_search-0.1.0.dist-info/METADATA
aws_multi_region_search-0.1.0.dist-info/WHEEL
aws_multi_region_search-0.1.0.dist-info/entry_points.txt
aws_multi_region_search-0.1.0.dist-info/RECORD
