Metadata-Version: 2.1
Name: aws-multi-region-search
Version: 0.1.0
Summary: AWS Multi Region Concurrent Query Tool
Home-page: https://github.com/skymoore/aws-search
License: MIT
Keywords: aws,cloud,multi-region,search,concurrent
Author: Sky Moore
Author-email: i@msky.me
Requires-Python: >=3.10,<4.0
Classifier: Intended Audience :: Developers
Classifier: License :: OSI Approved :: MIT License
Classifier: Natural Language :: English
Classifier: Programming Language :: Python :: 3
Classifier: Programming Language :: Python :: 3.10
Classifier: Programming Language :: Python :: 3.11
Classifier: Programming Language :: Python :: 3.12
Requires-Dist: boto3 (>=1.34.99,<2.0.0)
Requires-Dist: click (>=8.1.7,<9.0.0)
Project-URL: Repository, https://github.com/skymoore/aws-search
